gengine
