Metadata-Version: 2.1
Name: gamification-engine
Version: 0.4.0
Summary: The Gamification-Engine (gengine) provides an API for integrating any kinds of gamification features.
Home-page: https://www.gamification-software.com
Author: Marcel Sander, Jens Janiuk, Matthias Feldotto
Author-email: marcel@gamification-software.com
License: MIT
Keywords: web wsgi bfg pylons pyramid gamification
Platform: UNKNOWN
Classifier: Programming Language :: Python
Classifier: Framework :: Pyramid
Classifier: Topic :: Internet :: WWW/HTTP
Classifier: Topic :: Internet :: WWW/HTTP :: WSGI :: Application
Classifier: Topic :: Software Development :: Libraries
Classifier: Programming Language :: Python :: 3.6
Classifier: License :: OSI Approved :: MIT License
Provides-Extra: pushes
Provides-Extra: testing
Provides-Extra: auth
